{
  "id": "task-6",
  "title": "Improve review process to prevent bugs from slipping through",
  "description": "## Problem\nToo many bugs are currently getting through the review process and reaching production/later stages.\n\n## Goals\n- Analyze current review process to identify gaps\n- Implement improvements to catch bugs earlier\n- Consider automated checks, checklists, or additional review stages\n\n## Potential Solutions to Evaluate\n1. Enhanced automated testing (unit, integration, e2e)\n2. Review checklists or guidelines\n3. Additional review stages for high-risk changes\n4. Static analysis tools integration\n5. Pre-commit hooks for common issues\n6. Pair programming for complex features\n\n## Success Criteria\n- Measurable reduction in bugs found post-review\n- Clear documentation of improved review process\n- Team adoption of new practices",
  "type": "feature",
  "priority": "high",
  "state": "pending",
  "tags": [
    "quality",
    "process-improvement",
    "reviews"
  ],
  "createdAt": "2026-02-09T15:46:36.796604744-05:00",
  "updatedAt": "2026-02-09T15:46:36.796604789-05:00"
}